Metadata-Version: 1.1
Name: Kangana
Version: 0.0.2
Summary: Python package to encrypt and decrypt files.
Home-page: UNKNOWN
Author: moridb
Author-email: elogger@web.de
License: MIT
Keywords: kangana
Platform: UNKNOWN
Classifier: Development Status :: 5 - Production/Stable
Classifier: Intended Audience :: Education
Classifier: Operating System :: Microsoft :: Windows :: Windows 10
Classifier: License :: OSI Approved :: MIT License
Classifier: Programming Language :: Python :: 3
